clamdpy/__init__.py
clamdpy/exceptions.py
clamdpy/models.py
clamdpy/py.typed
clamdpy/sockets.py
clamdpy/typing.py
clamdpy-0.2.0.dist-info/METADATA
clamdpy-0.2.0.dist-info/WHEEL
clamdpy-0.2.0.dist-info/licenses/LICENSE
clamdpy-0.2.0.dist-info/RECORD
