Metadata-Version: 2.4
Name: clamdpy
Version: 0.2.0
Summary: A Python wrapper around clamd, the ClamAV daemon
Project-URL: Homepage, https://github.com/Viicos/clamdpy
Project-URL: Source, https://github.com/Viicos/clamdpy
Project-URL: Changelog, https://github.com/Viicos/clamdpy/blob/main/CHANGELOG.md
Author-email: Viicos <65306057+Viicos@users.noreply.github.com>
License: MIT License
License-File: LICENSE
Classifier: Development Status :: 4 - Beta
Classifier: License :: OSI Approved :: MIT License
Classifier: Operating System :: OS Independent
Classifier: Programming Language :: Python :: 3
Classifier: Programming Language :: Python :: 3 :: Only
Classifier: Programming Language :: Python :: 3.10
Classifier: Programming Language :: Python :: 3.11
Classifier: Programming Language :: Python :: 3.12
Classifier: Programming Language :: Python :: 3.13
Classifier: Programming Language :: Python :: 3.14
Classifier: Typing :: Typed
Requires-Python: >=3.10
